pyrol/TrilinosRepoVersion.txt
pyrol/__init__.py
pyrol/getTypeName.py
pyrol/pyrol.so
pyrol/unsupported.py
pyrol/include/OED_SplitComm.hpp
pyrol/include/ROL2_EnumMap.hpp
pyrol/include/ROL2_Enumeration.hpp
pyrol/include/ROL_AbsoluteValue.hpp
pyrol/include/ROL_AffineTransformConstraint.hpp
pyrol/include/ROL_AffineTransformConstraint_Def.hpp
pyrol/include/ROL_AffineTransformObjective.hpp
pyrol/include/ROL_AffineTransformObjective_Def.hpp
pyrol/include/ROL_Algorithm.hpp
pyrol/include/ROL_AlmostSureConstraint.hpp
pyrol/include/ROL_Arcsine.hpp
pyrol/include/ROL_AtomVector.hpp
pyrol/include/ROL_AugmentedLagrangian.hpp
pyrol/include/ROL_AugmentedLagrangianObjective.hpp
pyrol/include/ROL_AugmentedLagrangianStep.hpp
pyrol/include/ROL_AugmentedLagrangian_SimOpt.hpp
pyrol/include/ROL_AugmentedSystemOperator.hpp
pyrol/include/ROL_AugmentedSystemPrecOperator.hpp
pyrol/include/ROL_BLAS.hpp
pyrol/include/ROL_BPOE.hpp
pyrol/include/ROL_BVP.hpp
pyrol/include/ROL_BackTracking.hpp
pyrol/include/ROL_BackTracking_U.hpp
pyrol/include/ROL_BallIndicatorObjective.hpp
pyrol/include/ROL_BarzilaiBorwein.hpp
pyrol/include/ROL_BatchManager.hpp
pyrol/include/ROL_BatchStdVector.hpp
pyrol/include/ROL_Beale.hpp
pyrol/include/ROL_Beta.hpp
pyrol/include/ROL_BiCGSTAB.hpp
pyrol/include/ROL_BinaryConstraint.hpp
pyrol/include/ROL_BinaryConstraint_Def.hpp
pyrol/include/ROL_BinaryFunctions.hpp
pyrol/include/ROL_Bisection.hpp
pyrol/include/ROL_BisectionScalarMinimization.hpp
pyrol/include/ROL_BlockOperator.hpp
pyrol/include/ROL_BlockOperator2.hpp
pyrol/include/ROL_BlockOperator2Determinant.hpp
pyrol/include/ROL_BlockOperator2Diagonal.hpp
pyrol/include/ROL_BlockOperator2UnitLower.hpp
pyrol/include/ROL_BlockOperator2UnitUpper.hpp
pyrol/include/ROL_BoundConstraint.hpp
pyrol/include/ROL_BoundConstraint_Def.hpp
pyrol/include/ROL_BoundConstraint_Partitioned.hpp
pyrol/include/ROL_BoundConstraint_SimOpt.hpp
pyrol/include/ROL_BoundFletcher.hpp
rol_python-2025.9.10.dev1712.dist-info/METADATA
rol_python-2025.9.10.dev1712.dist-info/WHEEL
rol_python-2025.9.10.dev1712.dist-info/RECORD
rol_python-2025.9.10.dev1712.dist-info/licenses/LICENSE
