Metadata-Version: 2.4
Name: rol-python
Version: 2025.9.10.dev1712
Summary: Python interface to the Rapid Optimization Library (ROL)
Author: Christian Glusa, Kim Liegeois, Aurya Javeed
License-Expression: BSD-3-Clause
Classifier: Development Status :: 4 - Beta
Classifier: Programming Language :: Python :: 3.8
Classifier: Programming Language :: Python :: 3.9
Classifier: Programming Language :: Python :: 3.10
Classifier: Programming Language :: Python :: 3.11
Classifier: Programming Language :: Python :: 3.12
Classifier: Programming Language :: Python :: 3.13
Classifier: Programming Language :: Python :: 3.14
Requires-Python: >=3.8
Requires-Dist: numpy
